fluxerror/__init__.py
fluxerror/utils.py
fluxerror/delta_pco2/__init__.py
fluxerror/delta_pco2/frac.py
fluxerror/gas_transfer_velocity/__init__.py
fluxerror/gas_transfer_velocity/wanninkhof2014/__init__.py
fluxerror/gas_transfer_velocity/wanninkhof2014/_utils.py
fluxerror/gas_transfer_velocity/wanninkhof2014/derivative.py
fluxerror/gas_transfer_velocity/wanninkhof2014/frac.py
fluxerror/solubility/__init__.py
fluxerror/solubility/weiss1974/__init__.py
fluxerror/solubility/weiss1974/_utils.py
fluxerror/solubility/weiss1974/derivative.py
fluxerror/solubility/weiss1974/frac.py
fluxerror-0.1.dist-info/LICENSE
fluxerror-0.1.dist-info/METADATA
fluxerror-0.1.dist-info/WHEEL
fluxerror-0.1.dist-info/top_level.txt
fluxerror-0.1.dist-info/RECORD
